gcp_microservice_utils/__init__.py
gcp_microservice_utils/apigateway.py
gcp_microservice_utils/cloudsql.py
gcp_microservice_utils/logging.py
gcp_microservice_utils/py.typed
gcp_microservice_utils/token.py
gcp_microservice_utils/trace.py
gcp_microservice_utils-0.5.0.dist-info/LICENSE
gcp_microservice_utils-0.5.0.dist-info/METADATA
gcp_microservice_utils-0.5.0.dist-info/WHEEL
gcp_microservice_utils-0.5.0.dist-info/top_level.txt
gcp_microservice_utils-0.5.0.dist-info/RECORD
