Metadata-Version: 2.1
Name: gcp-microservice-utils
Version: 0.5.0
Summary: A Python library providing utilities to simplify the integration of various GCP Cloud services like, Cloud Logging, Cloud Trace, etc.
License: Apache 2.0
Classifier: Programming Language :: Python :: 3
Classifier: License :: OSI Approved :: Apache Software License
Classifier: Operating System :: OS Independent
Requires-Python: >=3.8
License-File: LICENSE
Requires-Dist: Flask >=3.0.0
Requires-Dist: google-auth ==2.36.0
Requires-Dist: google-cloud-logging ==3.11.3
Requires-Dist: google-cloud-trace ==1.14.0
Requires-Dist: PyMySQL ==1.1.1
Requires-Dist: types-PyMySQL ==1.1.0.20241103
Requires-Dist: cloud-sql-python-connector ==1.13.0
